{"number":"69","content":" Measuring examples  Table of contents Measurements Measurements code body common control { bundlesequence =&gt; { &quot;report&quot; }; } body monitor control { forgetrate =&gt; &quot;0.7&quot; ; histograms =&gt; &quot;true&quot; ; } bundle agent report { reports : &quot; Free memory read at $(mon.av_free_memory_watch) cf_monitord read $(mon.value_monitor_self_watch) &quot; ; } bundle monitor watch { measurements : # Test 1 - extract string matching &quot;/home/mark/tmp/testmeasure&quot; handle =&gt; &quot;blonk_watch&quot; , stream_type =&gt; &quot;file&quot; , data_type =&gt; &quot;string&quot; , history_type =&gt; &quot;weekly&quot; , units =&gt; &quot;blonks&quot; , match_value =&gt; find_blonks , action =&gt; sample_min ( &quot;10&quot; ); # Test 2 - follow a special process over time # using cfengine&#39;s process cache to avoid resampling &quot;/var/cfengine/state/cf_rootprocs&quot; handle =&gt; &quot;monitor_self_watch&quot; , stream_type =&gt; &quot;file&quot; , data_type =&gt; &quot;int&quot; , history_type =&gt; &quot;static&quot; , units =&gt; &quot;kB&quot; , match_value =&gt; proc_value ( &quot;.*cf-monitord.*&quot; , &quot;root \\s +[0-9.]+ \\s +[0-9.]+ \\s +[0-9.]+ \\s +[0-9.]+ \\s +([0-9]+).*&quot; ); # Test 3, discover disk device information &quot;/bin/df&quot; handle =&gt; &quot;free_disk_watch&quot; , stream_type =&gt; &quot;pipe&quot; , data_type =&gt; &quot;slist&quot; , history_type =&gt; &quot;static&quot; , units =&gt; &quot;device&quot; , match_value =&gt; file_system ; # Update this as often as possible # Test 4 &quot;/tmp/file&quot; handle =&gt; &quot;line_counter&quot; , stream_type =&gt; &quot;file&quot; , data_type =&gt; &quot;counter&quot; , match_value =&gt; scanlines ( &quot;MYLINE.*&quot; ), history_type =&gt; &quot;log&quot; ; } body match_value scanlines ( x ) { select_line_matching =&gt; &quot;^ $(x) $&quot; ; } body action sample_min ( x ) { ifelapsed =&gt; &quot; $(x) &quot; ; expireafter =&gt; &quot; $(x) &quot; ; } body match_value find_blonks { select_line_number =&gt; &quot;2&quot; ; extraction_regex =&gt; &quot;Blonk blonk ([blonk]+).*&quot; ; } body match_value free_memory # not willy! { select_line_matching =&gt; &quot;MemFree:.*&quot; ; extraction_regex =&gt; &quot;MemFree: \\s +([0-9]+).*&quot; ; } body match_value proc_value ( x , y ) { select_line_matching =&gt; &quot; $(x) &quot; ; extraction_regex =&gt; &quot; $(y) &quot; ; } body match_value file_system { select_line_matching =&gt; &quot;/.*&quot; ; extraction_regex =&gt; &quot;(.*)&quot; ; } ","title":"Measuring examples","headers":"Measuring examples  Measurements ","headersMap":{"top":"Measuring examples","measurements":" Measurements "},"uri":"examples-example-snippets-timing-counting-measuring.html","breadCrumbs":"<div id=\"breadcrumbs\"> <ul itemscope=\"\" itemtype=\"http://schema.org/BreadcrumbList\"> <li itemprop=\"itemListElement\" itemscope=\"\" itemtype=\"http://schema.org/ListItem\"> <a itemid=\"examples.html\" itemprop=\"item\" itemscope=\"\" itemtype=\"http://schema.org/Thing\" href=\"examples.html\"> <span itemprop=\"name\">Examples and tutorials</span> </a> </li> <li>/</li> <li itemprop=\"itemListElement\" itemscope=\"\" itemtype=\"http://schema.org/ListItem\"> <a itemid=\"examples-example-snippets.html\" itemprop=\"item\" itemscope=\"\" itemtype=\"http://schema.org/Thing\" href=\"examples-example-snippets.html\"> <span itemprop=\"name\">Example snippets</span> </a> </li> <li>/</li> <li itemprop=\"itemListElement\" itemscope=\"\" itemtype=\"http://schema.org/ListItem\"> <a itemid=\"examples-example-snippets-timing-counting-measuring.html\" itemprop=\"item\" itemscope=\"\" itemtype=\"http://schema.org/Thing\" href=\"examples-example-snippets-timing-counting-measuring.html\"> <span itemprop=\"name\">Measuring examples</span> </a> </li> </ul> </div>"}