{
      "bundles": [],
      "bodies": [
        {
          "sourcePath": "../core/masterfiles/lib/3.6/commands.cf",
          "line": 55,
          "namespace": "default",
          "name": "silent",
          "bodyType": "contain",
          "arguments": [],
          "contexts": [
            {
              "name": "any",
              "attributes": [
                {
                  "line": 57,
                  "lval": "no_output",
                  "rval": {
                    "type": "string",
                    "value": "true"
                  }
                }
              ]
            }
          ]
        },
        {
          "sourcePath": "../core/masterfiles/lib/3.6/commands.cf",
          "line": 62,
          "namespace": "default",
          "name": "in_dir",
          "bodyType": "contain",
          "arguments": [
            "s"
          ],
          "contexts": [
            {
              "name": "any",
              "attributes": [
                {
                  "line": 64,
                  "lval": "chdir",
                  "rval": {
                    "type": "string",
                    "value": "$(s)"
                  }
                }
              ]
            }
          ]
        },
        {
          "sourcePath": "../core/masterfiles/lib/3.6/commands.cf",
          "line": 69,
          "namespace": "default",
          "name": "in_dir_shell",
          "bodyType": "contain",
          "arguments": [
            "s"
          ],
          "contexts": [
            {
              "name": "any",
              "attributes": [
                {
                  "line": 71,
                  "lval": "chdir",
                  "rval": {
                    "type": "string",
                    "value": "$(s)"
                  }
                },
                {
                  "line": 72,
                  "lval": "useshell",
                  "rval": {
                    "type": "string",
                    "value": "true"
                  }
                }
              ]
            }
          ]
        },
        {
          "sourcePath": "../core/masterfiles/lib/3.6/commands.cf",
          "line": 77,
          "namespace": "default",
          "name": "silent_in_dir",
          "bodyType": "contain",
          "arguments": [
            "s"
          ],
          "contexts": [
            {
              "name": "any",
              "attributes": [
                {
                  "line": 79,
                  "lval": "chdir",
                  "rval": {
                    "type": "string",
                    "value": "$(s)"
                  }
                },
                {
                  "line": 80,
                  "lval": "no_output",
                  "rval": {
                    "type": "string",
                    "value": "true"
                  }
                }
              ]
            }
          ]
        },
        {
          "sourcePath": "../core/masterfiles/lib/3.6/commands.cf",
          "line": 85,
          "namespace": "default",
          "name": "in_shell",
          "bodyType": "contain",
          "arguments": [],
          "contexts": [
            {
              "name": "any",
              "attributes": [
                {
                  "line": 87,
                  "lval": "useshell",
                  "rval": {
                    "type": "string",
                    "value": "true"
                  }
                }
              ]
            }
          ]
        },
        {
          "sourcePath": "../core/masterfiles/lib/3.6/commands.cf",
          "line": 92,
          "namespace": "default",
          "name": "in_shell_bg",
          "bodyType": "contain",
          "arguments": [],
          "contexts": [
            {
              "name": "any",
              "attributes": [
                {
                  "line": 94,
                  "lval": "useshell",
                  "rval": {
                    "type": "string",
                    "value": "true"
                  }
                }
              ]
            }
          ]
        },
        {
          "sourcePath": "../core/masterfiles/lib/3.6/commands.cf",
          "line": 99,
          "namespace": "default",
          "name": "in_shell_and_silent",
          "bodyType": "contain",
          "arguments": [],
          "contexts": [
            {
              "name": "any",
              "attributes": [
                {
                  "line": 101,
                  "lval": "useshell",
                  "rval": {
                    "type": "string",
                    "value": "true"
                  }
                },
                {
                  "line": 102,
                  "lval": "no_output",
                  "rval": {
                    "type": "string",
                    "value": "true"
                  }
                }
              ]
            }
          ]
        },
        {
          "sourcePath": "../core/masterfiles/lib/3.6/commands.cf",
          "line": 107,
          "namespace": "default",
          "name": "in_dir_shell_and_silent",
          "bodyType": "contain",
          "arguments": [
            "dir"
          ],
          "contexts": [
            {
              "name": "any",
              "attributes": [
                {
                  "line": 109,
                  "lval": "useshell",
                  "rval": {
                    "type": "string",
                    "value": "true"
                  }
                },
                {
                  "line": 110,
                  "lval": "no_output",
                  "rval": {
                    "type": "string",
                    "value": "true"
                  }
                },
                {
                  "line": 111,
                  "lval": "chdir",
                  "rval": {
                    "type": "string",
                    "value": "$(dir)"
                  }
                }
              ]
            }
          ]
        },
        {
          "sourcePath": "../core/masterfiles/lib/3.6/commands.cf",
          "line": 116,
          "namespace": "default",
          "name": "setuid",
          "bodyType": "contain",
          "arguments": [
            "x"
          ],
          "contexts": [
            {
              "name": "any",
              "attributes": [
                {
                  "line": 118,
                  "lval": "exec_owner",
                  "rval": {
                    "type": "string",
                    "value": "$(x)"
                  }
                },
                {
                  "line": 119,
                  "lval": "useshell",
                  "rval": {
                    "type": "string",
                    "value": "false"
                  }
                }
              ]
            }
          ]
        },
        {
          "sourcePath": "../core/masterfiles/lib/3.6/commands.cf",
          "line": 124,
          "namespace": "default",
          "name": "setuid_sh",
          "bodyType": "contain",
          "arguments": [
            "x"
          ],
          "contexts": [
            {
              "name": "any",
              "attributes": [
                {
                  "line": 126,
                  "lval": "exec_owner",
                  "rval": {
                    "type": "string",
                    "value": "$(x)"
                  }
                },
                {
                  "line": 127,
                  "lval": "useshell",
                  "rval": {
                    "type": "string",
                    "value": "true"
                  }
                }
              ]
            }
          ]
        },
        {
          "sourcePath": "../core/masterfiles/lib/3.6/commands.cf",
          "line": 132,
          "namespace": "default",
          "name": "setuidgid_sh",
          "bodyType": "contain",
          "arguments": [
            "owner",
            "group"
          ],
          "contexts": [
            {
              "name": "any",
              "attributes": [
                {
                  "line": 134,
                  "lval": "exec_owner",
                  "rval": {
                    "type": "string",
                    "value": "$(owner)"
                  }
                },
                {
                  "line": 135,
                  "lval": "exec_group",
                  "rval": {
                    "type": "string",
                    "value": "$(group)"
                  }
                },
                {
                  "line": 136,
                  "lval": "useshell",
                  "rval": {
                    "type": "string",
                    "value": "true"
                  }
                }
              ]
            }
          ]
        },
        {
          "sourcePath": "../core/masterfiles/lib/3.6/commands.cf",
          "line": 141,
          "namespace": "default",
          "name": "jail",
          "bodyType": "contain",
          "arguments": [
            "owner",
            "root",
            "dir"
          ],
          "contexts": [
            {
              "name": "any",
              "attributes": [
                {
                  "line": 143,
                  "lval": "exec_owner",
                  "rval": {
                    "type": "string",
                    "value": "$(owner)"
                  }
                },
                {
                  "line": 144,
                  "lval": "useshell",
                  "rval": {
                    "type": "string",
                    "value": "true"
                  }
                },
                {
                  "line": 145,
                  "lval": "chdir",
                  "rval": {
                    "type": "string",
                    "value": "$(dir)"
                  }
                },
                {
                  "line": 146,
                  "lval": "chroot",
                  "rval": {
                    "type": "string",
                    "value": "$(root)"
                  }
                }
              ]
            }
          ]
        },
        {
          "sourcePath": "../core/masterfiles/lib/3.6/commands.cf",
          "line": 151,
          "namespace": "default",
          "name": "setuid_umask",
          "bodyType": "contain",
          "arguments": [
            "uid",
            "umask"
          ],
          "contexts": [
            {
              "name": "any",
              "attributes": [
                {
                  "line": 164,
                  "lval": "exec_owner",
                  "rval": {
                    "type": "string",
                    "value": "$(uid)"
                  }
                },
                {
                  "line": 165,
                  "lval": "umask",
                  "rval": {
                    "type": "string",
                    "value": "$(umask)"
                  }
                }
              ]
            }
          ]
        }
      ]
    }