{"number":"567","content":" Reset administrative credentials  Table of contents The default admin user can be reset to defaults using the following SQL. cfsettings-setadminpassword.sql INSERT INTO &quot;users&quot; ( &quot;username&quot; , &quot;password&quot; , &quot;salt&quot; , &quot;name&quot; , &quot;email&quot; , &quot;external&quot; , &quot;active&quot; , &quot;roles&quot; , &quot;changetimestamp&quot; ) SELECT &#39;admin&#39; , &#39;SHA=aa459b45ecf9816d472c2252af0b6c104f92a6faf2844547a03338e42e426f52&#39; , &#39;eWAbKQmxNP&#39; , &#39;admin&#39; , &#39;admin@organisation.com&#39; , false , &#39;1&#39; , &#39;{admin,cf_remoteagent}&#39; , now () ON CONFLICT ( username , external ) DO UPDATE SET password = &#39;SHA=aa459b45ecf9816d472c2252af0b6c104f92a6faf2844547a03338e42e426f52&#39; , salt = &#39;eWAbKQmxNP&#39; ; To reset the CFEngine admin user run the following sql as root on your hub command psql cfsettings &lt; cfsettings-setadminpassword.sql Internal credentials Two internal credentials are present in an Enterprise Hub: Mission Portal API credentials and CFE Robot credentials. If these credentials are not synchronized between configuration files and database, errors can occur in the Mission Portal UI as well as in hub policy. Rotating these credentials is optional and can be performed at an interval based on your specific security policy. Mission Portal API credentials These credentials enable Mission Portal to authenticate to the backend API. If these credentials are not synchronized properly you can get &quot;Authentication failed&quot; messages in the Mission Portal UI. To rotate these credentials execute the following shell script on the hub and then restart the system with systemctl restart cfengine3 or similar. rotate_mp_credentials.sh #!/usr/bin/env bash pwgen () { dd if = /dev/urandom bs = 1024 count = 1 2 &gt;/dev/null | tr -dc &#39;a-zA-Z0-9&#39; | fold -w $1 | head -n 1 } PREFIX = /var/cfengine # adjust if needed, this is the default MP_PW = ` pwgen 40 ` SECRETS_FILE = &quot; $PREFIX /httpd/secrets.ini&quot; # 3.16 version and newer if [ -f &quot; $SECRETS_FILE &quot; ] ; then sed -i &quot;/mp_client_secret/s/=.*/= $MP_PW /&quot; $SECRETS_FILE else APPSETTINGS_FILE = &quot; $PREFIX /httpd/htdocs/application/config/appsettings.php&quot; sed -i &quot;/MP_CLIENT_SECRET/c\\$config[&#39;MP_CLIENT_SECRET&#39;] = &#39; $MP_PW &#39;;&quot; $APPSETTINGS_FILE fi echo &quot;UPDATE oauth_clients SET client_secret = &#39; $MP_PW &#39; where client_id = &#39;MP&#39;&quot; | $PREFIX /bin/psql cfsettings CFE Robot credentials These credentials are used by PHP CLI scripts to authenticate to the backend API. If these credentials are out of sync or incorrect you will see errors like &quot;500 Internal Server Error&quot; in /var/cfengine/httpd/logs/application/ logs. Execute the following shell script to rotate and synchronize the CFE Robot credentials and then restart the system with systemctl restart cfengine3 or similar. rotate_cfrobot_credentials.sh #!/usr/bin/env bash pwgen () { dd if = /dev/urandom bs = 1024 count = 1 2 &gt;/dev/null | tr -dc &#39;a-zA-Z0-9&#39; | fold -w $1 | head -n 1 } PREFIX = /var/cfengine # adjust if needed, this is the default pwhash () { echo -n &quot; $1 &quot; | &quot; $PREFIX /bin/openssl&quot; dgst -sha256 | awk &#39;{print $2}&#39; } CFE_ROBOT_PW = ` pwgen 40 ` SECRETS_FILE = &quot; $PREFIX /httpd/secrets.ini&quot; # 3.16 version and newer if [ -f &quot; $SECRETS_FILE &quot; ] ; then sed -i &quot;/cf_robot_password/s/=.*/= $CFE_ROBOT_PW /&quot; $SECRETS_FILE else CFROBOT_FILE = &quot; $PREFIX /httpd/htdocs/application/config/cf_robot.php&quot; sed -i &quot;/CFE_ROBOT_PASSWORD/c\\$config[&#39;CFE_ROBOT_PASSWORD&#39;] = \\&quot; $CFE_ROBOT_PW \\&quot;;&quot; $CFROBOT_FILE fi CFE_ROBOT_PW_SALT = ` pwgen 10 ` CFE_ROBOT_PW_HASH = ` pwhash &quot; $CFE_ROBOT_PW_SALT$CFE_ROBOT_PW &quot; ` echo &quot;UPDATE users SET password = &#39;SHA= $CFE_ROBOT_PW_HASH &#39;, salt = &#39; $CFE_ROBOT_PW_SALT &#39; WHERE username = &#39;CFE_ROBOT&#39;&quot; | &quot; $PREFIX /bin/psql&quot; cfsettings ","title":"Reset administrative credentials","headers":"Reset administrative credentials  Internal credentials   Mission Portal API credentials   CFE Robot credentials ","headersMap":{"top":"Reset administrative credentials","internal-credentials":" Internal credentials ","mission-portal-api-credentials":" Mission Portal API credentials ","cfe-robot-credentials":" CFE Robot credentials "},"uri":"web-ui-hub_administration-reset-admin-creds.html","breadCrumbs":"<div id=\"breadcrumbs\"> <ul itemscope=\"\" itemtype=\"http://schema.org/BreadcrumbList\"> <li itemprop=\"itemListElement\" itemscope=\"\" itemtype=\"http://schema.org/ListItem\"> <a itemid=\"web-ui.html\" itemprop=\"item\" itemscope=\"\" itemtype=\"http://schema.org/Thing\" href=\"web-ui.html\"> <span itemprop=\"name\">Web UI</span> </a> </li> <li>/</li> <li itemprop=\"itemListElement\" itemscope=\"\" itemtype=\"http://schema.org/ListItem\"> <a itemid=\"web-ui-hub_administration.html\" itemprop=\"item\" itemscope=\"\" itemtype=\"http://schema.org/Thing\" href=\"web-ui-hub_administration.html\"> <span itemprop=\"name\">Hub administration</span> </a> </li> <li>/</li> <li itemprop=\"itemListElement\" itemscope=\"\" itemtype=\"http://schema.org/ListItem\"> <a itemid=\"web-ui-hub_administration-reset-admin-creds.html\" itemprop=\"item\" itemscope=\"\" itemtype=\"http://schema.org/Thing\" href=\"web-ui-hub_administration-reset-admin-creds.html\"> <span itemprop=\"name\">Reset administrative credentials</span> </a> </li> </ul> </div>"}